MANIFEST.in
README.rst
setup.py
deltacloud_heat/__init__.py
deltacloud_heat/client.py
deltacloud_heat/nova.py
deltacloud_heat.egg-info/PKG-INFO
deltacloud_heat.egg-info/SOURCES.txt
deltacloud_heat.egg-info/dependency_links.txt
deltacloud_heat.egg-info/requires.txt
deltacloud_heat.egg-info/top_level.txt