Metadata-Version: 1.1
Name: deltacloud-heat
Version: 0.1.0
Summary: Deltacloud backend for Heat
Home-page: https://github.com/tomassedovic/deltacloud_heat
Author: Tomas Sedovic
Author-email: tomas@sedovic.cz
License: UNKNOWN
Platform: UNKNOWN
Classifier: Programming Language :: Python
Classifier: Development Status :: 3 - Alpha
Classifier: Environment :: Other Environment
Classifier: Intended Audience :: Developers
Classifier: License :: OSI Approved :: Apache Software License
Classifier: Operating System :: OS Independent
Classifier: Topic :: Software Development :: Libraries :: Python Modules
